romscom/__about__.py
romscom/__init__.py
romscom/rcutils.py
romscom/romscom.py
romscom/varinfo.py
romscom-2025.6.4.dist-info/METADATA
romscom-2025.6.4.dist-info/WHEEL
romscom-2025.6.4.dist-info/licenses/LICENSE
romscom-2025.6.4.dist-info/RECORD
