Metadata-Version: 2.4
Name: romscom
Version: 2025.6.4
Summary: ROMS Communication Toolbox: Python utilities to format text input for and run simulations of the Regional Ocean Modeling System (ROMS)
Project-URL: Documentation, https://github.com/beringnpz/romscom/#readme
Project-URL: Issues, https://github.com/beringnpz/romscom/issues
Project-URL: Source, https://github.com/beringnpz/romscom
Author-email: Kelly Kearney <kelly.kearney@noaa.gov>
License-Expression: CC0-1.0
License-File: LICENSE
Keywords: ROMS,modeling,ocean,regional
Classifier: Development Status :: 4 - Beta
Classifier: Programming Language :: Python
Classifier: Programming Language :: Python :: 3.8
Classifier: Programming Language :: Python :: 3.9
Classifier: Programming Language :: Python :: 3.10
Classifier: Programming Language :: Python :: 3.11
Classifier: Programming Language :: Python :: 3.12
Classifier: Programming Language :: Python :: Implementation :: CPython
Classifier: Programming Language :: Python :: Implementation :: PyPy
Requires-Python: >=3.8
Requires-Dist: netcdf4
Requires-Dist: numpy
Requires-Dist: pyyaml
